JAX_CRPS/__init__.py
JAX_CRPS/core.py
jax_crps-0.1.1.dist-info/licenses/LICENSE
jax_crps-0.1.1.dist-info/METADATA
jax_crps-0.1.1.dist-info/WHEEL
jax_crps-0.1.1.dist-info/top_level.txt
jax_crps-0.1.1.dist-info/RECORD
