Metadata-Version: 2.4
Name: JAX_CRPS
Version: 0.1.1
Summary: A simple package implementing the Continuous Ranked Probability Score (CRPS) using JAX
Author: James Woodfield
Author-email: notmyemail@dontwebscrapeme.com
Classifier: Programming Language :: Python :: 3
Classifier: Operating System :: OS Independent
Requires-Python: >=3.6
License-File: LICENSE
Requires-Dist: jax>=0.4.0
Dynamic: author
Dynamic: author-email
Dynamic: classifier
Dynamic: license-file
Dynamic: requires-dist
Dynamic: requires-python
Dynamic: summary
